aspyx_event/__init__.py
aspyx_event/event.py
aspyx_event/event_amqp.py
aspyx_event/event_nsq.py
aspyx_event/event_stomp.py
aspyx_event/event_ws.py
aspyx_event-0.9.8.dist-info/METADATA
aspyx_event-0.9.8.dist-info/WHEEL
aspyx_event-0.9.8.dist-info/licenses/LICENSE
aspyx_event-0.9.8.dist-info/RECORD
