Metadata-Version: 2.4
Name: aspyx_event
Version: 0.9.8
Summary: Aspyx event framework
Author-email: Andreas Ernst <andreas.ernst7@gmail.com>
License: MIT License
License-File: LICENSE
Requires-Python: >=3.9
Requires-Dist: ansq>=0.3.0
Requires-Dist: aspyx>=1.9.8
Requires-Dist: cbor2>=5.4.0
Requires-Dist: python-qpid-proton>=0.40.0
Requires-Dist: stomp-py>=8.2.0
